crackertool
