Metadata-Version: 2.1
Name: crackertool
Version: 0.2
Summary: A PIP FOR INSTALLING CRACKER-TOOL OF CRACKER911181
Home-page: https://pypi.org/project/crackertool
Download-URL: https://pypi.org/project/crackertool
Author: cracker911181
Author-email: admin@cracker911181.cf
License: MIT
License-File: LICENSE
